irekua_permissions/__init__.py
irekua_permissions/general.py
irekua_permissions/licences.py
irekua_permissions/sites.py
irekua_permissions/version.py
irekua_permissions/annotations/__init__.py
irekua_permissions/annotations/annotations.py
irekua_permissions/annotations/tools.py
irekua_permissions/annotations/votes.py
irekua_permissions/data_collections/__init__.py
irekua_permissions/data_collections/data_collections.py
irekua_permissions/data_collections/devices.py
irekua_permissions/data_collections/metacollections.py
irekua_permissions/data_collections/sites.py
irekua_permissions/data_collections/users.py
irekua_permissions/devices/__init__.py
irekua_permissions/devices/brands.py
irekua_permissions/devices/devices.py
irekua_permissions/devices/physical_devices.py
irekua_permissions/items/__init__.py
irekua_permissions/items/items.py
irekua_permissions/items/secondary_items.py
irekua_permissions/items/sources.py
irekua_permissions/items/tags.py
irekua_permissions/models/__init__.py
irekua_permissions/models/model_predictions.py
irekua_permissions/models/model_versions.py
irekua_permissions/models/models.py
irekua_permissions/object_types/__init__.py
irekua_permissions/object_types/annotations.py
irekua_permissions/object_types/devices.py
irekua_permissions/object_types/entailments.py
irekua_permissions/object_types/events.py
irekua_permissions/object_types/items.py
irekua_permissions/object_types/licences.py
irekua_permissions/object_types/sites.py
irekua_permissions/object_types/terms.py
irekua_permissions/object_types/data_collections/__init__.py
irekua_permissions/object_types/data_collections/collection_types.py
irekua_permissions/object_types/data_collections/device_types.py
irekua_permissions/object_types/data_collections/item_types.py
irekua_permissions/object_types/data_collections/roles.py
irekua_permissions/object_types/sampling_events/__init__.py
irekua_permissions/object_types/sampling_events/device_types.py
irekua_permissions-0.1.2.dist-info/LICENCE
irekua_permissions-0.1.2.dist-info/METADATA
irekua_permissions-0.1.2.dist-info/WHEEL
irekua_permissions-0.1.2.dist-info/top_level.txt
irekua_permissions-0.1.2.dist-info/RECORD
